[{"id":1730392888049,"title":"car blue","price":"20000","yearProduction":"2014","licenseNumber":"aa1111aa","imgSrc":"/1730392888040-blue.jpg"},{"id":1730392919559,"title":"red car","price":"18000","yearProduction":"2021","licenseNumber":"dd2021dd","imgSrc":"/1730392919548-Toyota_Corolla.jpg"},{"id":1730392976270,"title":"white car","price":"23000","yearProduction":"2022","licenseNumber":"jj2022jj","imgSrc":"/1730392976261-CPO4x3.jpeg"},{"id":1730392999763,"title":"test22","price":"2132","yearProduction":"2013","licenseNumber":"ff4444ff","imgSrc":"/1730393325675-blue.jpg"},{"id":1730393517605,"title":"kk5555kk","price":"5555","yearProduction":"2014","licenseNumber":"kk5555kk","imgSrc":"/1730393517599-blue.jpg"}]